minexr/__init__.py
minexr/buffer.py
minexr/reader.py
minexr-1.0.2.dist-info/LICENSE
minexr-1.0.2.dist-info/METADATA
minexr-1.0.2.dist-info/WHEEL
minexr-1.0.2.dist-info/top_level.txt
minexr-1.0.2.dist-info/RECORD
