Metadata-Version: 2.1
Name: minexr
Version: 1.0.2
Summary: Minimal, standalone OpenEXR reader for single-part, uncompressed scan line files.
Home-page: https://github.com/cheind/py-minexr
Author: Christoph Heindl
License-File: LICENSE
Requires-Dist: numpy
